aggregation_agent/__init__.py
aggregation_agent/agent.py
aggregation_agent/config.py
aggregation_agent/constants.py
aggregation_agent/models.py
aggregation_agent-0.1.8.dist-info/METADATA
aggregation_agent-0.1.8.dist-info/WHEEL
aggregation_agent-0.1.8.dist-info/RECORD
