Metadata-Version: 2.4
Name: aggregation-agent
Version: 0.1.8
Summary: StepFn Aggregation Agent
Project-URL: Homepage, https://github.com/stepfnAI/aggregation_agent
Project-URL: Bug Tracker, https://github.com/stepfnAI/aggregation_agent/issues
Author: StepFn AI
Requires-Python: >=3.10
Requires-Dist: pandas
Requires-Dist: pydantic-settings
Requires-Dist: sfn-blueprint>=0.7.4
Provides-Extra: dev
Requires-Dist: black>=23.0.0; extra == 'dev'
Requires-Dist: flake8>=6.0.0; extra == 'dev'
Requires-Dist: mypy>=1.0.0; extra == 'dev'
Requires-Dist: pytest-cov>=4.0.0; extra == 'dev'
Requires-Dist: pytest>=7.0.0; extra == 'dev'
